simplysql/__init__.py
simplysql/base_interfaces/__init__.py
simplysql/base_interfaces/database.py
simplysql/base_interfaces/datatable.py
simplysql/conn_interfaces/__init__.py
simplysql/conn_interfaces/connection.py
simplysql/vector_interfaces/__init__.py
simplysql/vector_interfaces/datacolumn.py
simplysql/vector_interfaces/datacolumns.py
simplysql/vector_interfaces/datarow.py
simplysql/vector_interfaces/datarows.py
simplysql-0.1.3.dist-info/LICENSE
simplysql-0.1.3.dist-info/LICENSE.txt
simplysql-0.1.3.dist-info/METADATA
simplysql-0.1.3.dist-info/WHEEL
simplysql-0.1.3.dist-info/top_level.txt
simplysql-0.1.3.dist-info/RECORD
